mixnode/__init__.py
mixnode/api_client.py
mixnode/error.py
mixnode_py_sdk-1.0.2.dist-info/LICENSE
mixnode_py_sdk-1.0.2.dist-info/METADATA
mixnode_py_sdk-1.0.2.dist-info/WHEEL
mixnode_py_sdk-1.0.2.dist-info/top_level.txt
mixnode_py_sdk-1.0.2.dist-info/RECORD
