Metadata-Version: 2.1
Name: mixnode-py-sdk
Version: 1.0.2
Summary: Mixnode Python SDK
Home-page: https://github.com/Mixnode/mixnode-py-sdk
Author: Mixnode Technologies Inc.
Author-email: devsteelcoder@gmail.com
License: UNKNOWN
Download-URL: https://github.com/Mixnode/mixnode-py-sdk
Platform: UNKNOWN
Classifier: Natural Language :: English
Classifier: Operating System :: OS Independent
Classifier: Programming Language :: Python
Classifier: Programming Language :: Python :: 2.7
Classifier: Programming Language :: Python :: 3.4
Classifier: Programming Language :: Python :: 3.5
Classifier: Programming Language :: Python :: 3.6
Classifier: Programming Language :: Python :: 3.7
Classifier: Topic :: Software Development :: Libraries :: Python Modules
Requires-Dist: requests
